chrisversiontest/__init__.py
chrisversiontest/__version__.py
chrisversiontest/entrypoint.py
chrisversiontest/__pycache__/__init__.cpython-311.pyc
chrisversiontest/__pycache__/entrypoint.cpython-311.pyc
chrisversiontest-0.1.5.dist-info/LICENSE
chrisversiontest-0.1.5.dist-info/METADATA
chrisversiontest-0.1.5.dist-info/WHEEL
chrisversiontest-0.1.5.dist-info/entry_points.txt
chrisversiontest-0.1.5.dist-info/top_level.txt
chrisversiontest-0.1.5.dist-info/RECORD
