Metadata-Version: 2.1
Name: chrisversiontest
Version: 0.1.5
Summary: Testing some versioning stuff in isolation
License: Apache 2.0
Project-URL: Homepage, https://github.com/chris11-taylor-nttd/py-versioning
Classifier: Programming Language :: Python :: 3
Classifier: License :: OSI Approved :: MIT License
Classifier: Operating System :: OS Independent
Requires-Python: >=3.11
License-File: LICENSE
Requires-Dist: gitpython >=3.1
Requires-Dist: semver >=3.0
Requires-Dist: setuptools-scm >=8.1
Provides-Extra: dev
Requires-Dist: pytest ~=7.0 ; extra == 'dev'
Requires-Dist: pytest-mock ~=3.0 ; extra == 'dev'
Requires-Dist: responses ~=0.24.0 ; extra == 'dev'
Requires-Dist: black >=23.11.0 ; extra == 'dev'
Requires-Dist: isort >=5.12.0 ; extra == 'dev'
Requires-Dist: faker >=24.14 ; extra == 'dev'
